LICENSE
README.md
setup.cfg
setup.py
UserCenterApi.egg-info/PKG-INFO
UserCenterApi.egg-info/SOURCES.txt
UserCenterApi.egg-info/dependency_links.txt
UserCenterApi.egg-info/top_level.txt
userCenterApi/__init__.py
userCenterApi/api.py
userCenterApi/base.py
userCenterApi/url_settings.py
userCenterApi/utils.py