Metadata-Version: 2.1
Name: UserCenterApi
Version: 0.0.2
Summary: pujian用户中心集成SDK
Home-page: https://github.com/pypa/sampleproject
Author: FANG
Author-email: 1921535208@qq.com
License: UNKNOWN
Platform: UNKNOWN
Classifier: Programming Language :: Python :: 3
Classifier: License :: OSI Approved :: MIT License
Classifier: Operating System :: OS Independent
Requires-Python: >=3.6
License-File: LICENSE
